osm_clipper.py
osm_clipper-0.1.0.dist-info/LICENSE
osm_clipper-0.1.0.dist-info/METADATA
osm_clipper-0.1.0.dist-info/WHEEL
osm_clipper-0.1.0.dist-info/entry_points.txt
osm_clipper-0.1.0.dist-info/top_level.txt
osm_clipper-0.1.0.dist-info/RECORD
