Metadata-Version: 2.1
Name: osm-clipper
Version: 0.1.0
Summary: Small python tool to clip pre-defined areas from the planet osm file.
Home-page: https://github.com/ElcoK/osm_clipper
Author: Elco Koks
Author-email: elcokoks@gmail.com
License: MIT License
Platform: UNKNOWN
Classifier: Development Status :: 3 - Alpha
Classifier: Intended Audience :: Developers
Classifier: License :: OSI Approved :: MIT License
Classifier: Programming Language :: Python
Classifier: Programming Language :: Python :: 3
Classifier: Topic :: Scientific/Engineering :: GIS
Classifier: Topic :: Utilities
Requires-Dist: shapely (>=1.6)
Requires-Dist: geopandas (>=0.8.0)
Requires-Dist: pandas (>=1.0.0)
Requires-Dist: numpy (>=1.15.2)
Requires-Dist: pygeos (>=0.7.1)
Requires-Dist: tqdm (>=4.30.0)
Requires-Dist: urllib3 (>=1.25geopy>2.0.0)
